encr/__init__.py
encr/encr.py
encr-0.1.0.1.dist-info/METADATA
encr-0.1.0.1.dist-info/WHEEL
encr-0.1.0.1.dist-info/licenses/LICENSE
encr-0.1.0.1.dist-info/RECORD
