Metadata-Version: 2.1
Name: encr
Version: 0.1.0.1
Summary: A small package for safe data serialization and encryption
Project-URL: Homepage, https://github.com/Malasaur/encr
Project-URL: Bug Tracker, https://github.com/Malasaur/encr/issues
Author-email: Silvio Amuntenci <amuntenci.silvio@gmail.com>
License-File: LICENSE
Classifier: License :: OSI Approved :: GNU General Public License v3 (GPLv3)
Classifier: Operating System :: OS Independent
Classifier: Programming Language :: Python :: 3
Requires-Python: >=3.7
